timex_lca/__init__.py
timex_lca/dynamic_biosphere_builder.py
timex_lca/dynamic_characterization.py
timex_lca/edge_extractor.py
timex_lca/matrix_modifier.py
timex_lca/remapping.py
timex_lca/timeline_builder.py
timex_lca/timex_lca.py
timex_lca/utils.py
timex_lca/data/hodnebrog20.csv
timex_lca-1.0.0.dist-info/LICENSE
timex_lca-1.0.0.dist-info/METADATA
timex_lca-1.0.0.dist-info/WHEEL
timex_lca-1.0.0.dist-info/top_level.txt
timex_lca-1.0.0.dist-info/RECORD
