Metadata-Version: 2.1
Name: timex_lca
Version: 1.0.0
Summary: Time-explicit Life Cycle Assessment
Author: Amelie Müller, Arthur Jakobs
Author-email: Timo Diepers <timo.diepers@ltt.rwth-aachen.de>
Maintainer: Amelie Müller
Maintainer-email: Timo Diepers <timo.diepers@ltt.rwth-aachen.de>
Project-URL: source, https://github.com/TimoDiepers/timex
Project-URL: homepage, https://github.com/TimoDiepers/timex
Project-URL: tracker, https://github.com/TimoDiepers/timex/issues
Keywords: brightway,Life Cycle Assessment,LCA,time-explicit,dynamic,prospective
Classifier: Development Status :: 3 - Alpha
Classifier: Intended Audience :: Science/Research
Classifier: License :: OSI Approved :: BSD License
Classifier: Natural Language :: English
Classifier: Programming Language :: Python :: 3
Classifier: Operating System :: OS Independent
Classifier: Topic :: Scientific/Engineering
Requires-Python: >=3.10
License-File: LICENSE
Requires-Dist: platformdirs
Requires-Dist: requests
Requires-Dist: sphinx-autoapi
Requires-Dist: myst-nb
Provides-Extra: dev
Requires-Dist: pre-commit ; extra == 'dev'
Requires-Dist: pylint ; extra == 'dev'
Provides-Extra: docs
Requires-Dist: ipython ; extra == 'docs'
Requires-Dist: pydata-sphinx-theme ; extra == 'docs'
Requires-Dist: myst-parser ; extra == 'docs'
Requires-Dist: sphinx-click ; extra == 'docs'
Requires-Dist: sphinx-design ; extra == 'docs'
Requires-Dist: sphinx-notfound-page ; extra == 'docs'
Requires-Dist: sphinx-favicon ; extra == 'docs'
Requires-Dist: sphinx-copybutton ; extra == 'docs'
Requires-Dist: sphinx-autobuild ; extra == 'docs'
Provides-Extra: testing
Requires-Dist: setuptools ; extra == 'testing'
Requires-Dist: pytest ; extra == 'testing'
Requires-Dist: pytest-cov ; extra == 'testing'
